authup/__init__.py
authup/authup.py
authup/client/__init__.py
authup/client/base_resource_client.py
authup/client/client.py
authup/client/resource_clients/__init__.py
authup/client/resource_clients/realm.py
authup/permissions.py
authup/plugins/__init__.py
authup/plugins/asgi.py
authup/plugins/fastapi.py
authup/plugins/flask.py
authup/plugins/httpx.py
authup/plugins/requests.py
authup/schemas/__init__.py
authup/schemas/realm.py
authup/schemas/token.py
authup/schemas/user.py
authup/settings.py
authup/tests/__init__.py
authup/tests/client/__init__.py
authup/tests/client/test_client.py
authup/tests/client/test_realm_client.py
authup/tests/conftest.py
authup/tests/plugins/__init__.py
authup/tests/plugins/test_asgi.py
authup/tests/plugins/test_fastapi.py
authup/tests/plugins/test_httpx.py
authup/tests/plugins/test_requests.py
authup/tests/test_authup.py
authup/tests/test_permissions.py
authup/tests/test_settings.py
authup/tests/test_token.py
authup/token.py
authup-0.5.1.dist-info/METADATA
authup-0.5.1.dist-info/WHEEL
authup-0.5.1.dist-info/RECORD
