Metadata-Version: 2.1
Name: authup
Version: 0.5.1
Summary: Python plugins for the Authup authentication and authorization framework
Home-page: https://authup.org
License: MIT
Author: Michael Graf
Author-email: michael.graf3110@gmail.com
Requires-Python: >=3.7,<4.0
Classifier: License :: OSI Approved :: MIT License
Classifier: Programming Language :: Python :: 3
Classifier: Programming Language :: Python :: 3.7
Classifier: Programming Language :: Python :: 3.8
Classifier: Programming Language :: Python :: 3.9
Classifier: Programming Language :: Python :: 3.10
Classifier: Programming Language :: Python :: 3.11
Provides-Extra: all
Provides-Extra: asgi
Provides-Extra: fastapi
Provides-Extra: flask
Provides-Extra: requests
Requires-Dist: asgiref (>=3.6.0,<4.0.0)
Requires-Dist: fastapi (>=0.87.0) ; extra == "fastapi" or extra == "all"
Requires-Dist: flask (>=2.0.0,<3.0.0) ; extra == "flask" or extra == "all"
Requires-Dist: httpx
Requires-Dist: pydantic
Requires-Dist: requests ; extra == "requests" or extra == "all"
Project-URL: Repository, https://github.com/migraf/authup-py.git
